skytemple_icons/__init__.py
skytemple_icons/hicolor/128x128/apps/skytemple-action-unavailable-symbolic.symbolic.png
skytemple_icons/hicolor/128x128/apps/skytemple-audio-volume-high-symbolic.symbolic.png
skytemple_icons/hicolor/128x128/apps/skytemple-audio-volume-low-symbolic.symbolic.png
skytemple_icons/hicolor/128x128/apps/skytemple-audio-volume-medium-symbolic.symbolic.png
skytemple_icons/hicolor/128x128/apps/skytemple-audio-volume-mute-symbolic.symbolic.png
skytemple_icons/hicolor/128x128/apps/skytemple-copy-settings-symbolic.symbolic.png
skytemple_icons/hicolor/128x128/apps/skytemple-debugger-debug-symbolic.symbolic.png
skytemple_icons/hicolor/128x128/apps/skytemple-debugger-disable-breaks-symbolic.symbolic.png
skytemple_icons/hicolor/128x128/apps/skytemple-debugger-step-into-symbolic.symbolic.png
skytemple_icons/hicolor/128x128/apps/skytemple-debugger-step-next-symbolic.symbolic.png
skytemple_icons/hicolor/128x128/apps/skytemple-debugger-step-out-symbolic.symbolic.png
skytemple_icons/hicolor/128x128/apps/skytemple-debugger-step-over-symbolic.symbolic.png
skytemple_icons/hicolor/128x128/apps/skytemple-dialog-error-symbolic.symbolic.png
skytemple_icons/hicolor/128x128/apps/skytemple-document-edit-symbolic.symbolic.png
skytemple_icons/hicolor/128x128/apps/skytemple-dungeon-wall-symbolic.symbolic.png
skytemple_icons/hicolor/128x128/apps/skytemple-e-actor-symbolic.symbolic.png
skytemple_icons/hicolor/128x128/apps/skytemple-e-bgp-symbolic.symbolic.png
skytemple_icons/hicolor/128x128/apps/skytemple-e-dungeon-fixed-floor-symbolic.symbolic.png
skytemple_icons/hicolor/128x128/apps/skytemple-e-dungeon-floor-symbolic.symbolic.png
skytemple_icons/hicolor/128x128/apps/skytemple-e-dungeon-symbolic.symbolic.png
skytemple_icons/hicolor/128x128/apps/skytemple-e-dungeon-tileset-symbolic.symbolic.png
skytemple_icons/hicolor/128x128/apps/skytemple-e-event-symbolic.symbolic.png
skytemple_icons/hicolor/128x128/apps/skytemple-e-graphics-symbolic.symbolic.png
skytemple_icons-1.2.0.dist-info/LICENSE_CC
skytemple_icons-1.2.0.dist-info/LICENSE_GPLv3
skytemple_icons-1.2.0.dist-info/METADATA
skytemple_icons-1.2.0.dist-info/WHEEL
skytemple_icons-1.2.0.dist-info/top_level.txt
skytemple_icons-1.2.0.dist-info/RECORD
