Metadata-Version: 2.1
Name: skytemple-icons
Version: 1.2.0
Summary: Icons for SkyTemple
Home-page: https://github.com/SkyTemple/skytemple-icons/
License: UNKNOWN
Platform: UNKNOWN
Classifier: License :: OSI Approved :: GNU General Public License v3 or later (GPLv3+)
